linpde_gp/__init__.py
linpde_gp/_version.py
linpde_gp/randvars.py
linpde_gp/typing.py
linpde_gp/domains/__init__.py
linpde_gp/domains/_asdomain.py
linpde_gp/domains/_box.py
linpde_gp/domains/_cartesian_product.py
linpde_gp/domains/_domain.py
linpde_gp/domains/_interval.py
linpde_gp/domains/_point.py
linpde_gp/functions/__init__.py
linpde_gp/functions/_affine.py
linpde_gp/functions/_constant.py
linpde_gp/functions/_fourier.py
linpde_gp/functions/_jax.py
linpde_gp/functions/_jax_arithmetic.py
linpde_gp/functions/_linfunctls.py
linpde_gp/functions/_piecewise.py
linpde_gp/functions/_polynomial.py
linpde_gp/functions/_stack.py
linpde_gp/functions/_truncated_gmm.py
linpde_gp/functions/bases/__init__.py
linpde_gp/functions/bases/_fem.py
linpde_gp/functions/linfuncops/__init__.py
linpde_gp/functions/linfuncops/_registry.py
linpde_gp/linalg/__init__.py
linpde_gp/linalg/_helpers.py
linpde_gp/linalg/solvers/__init__.py
linpde_gp/linalg/solvers/_bayescg.py
linpde_gp/linalg/solvers/_cg.py
linpde_gp/linalg/solvers/_probabilistic_linear_solver.py
linpde_gp/linalg/solvers/_problinsolve.py
linpde_gp/linalg/solvers/belief_updates.py
linpde_gp/linalg/solvers/beliefs.py
linpde_gp/linalg/solvers/observation_ops.py
linpde_gp/linalg/solvers/policies.py
linpde_gp/linalg/solvers/stopping_criteria.py
linpde_gp/linfuncops/__init__.py
linpde_gp/linfuncops/_arithmetic.py
linpde_gp/linfuncops/_identity.py
linpde_gp/linfuncops/_linfuncop.py
linpde_gp/linfuncops/_select_output.py
linpde_gp/linfuncops/diffops/__init__.py
linpde_gp/linfuncops/diffops/_arithmetic.py
linpde_gp/linfuncops/diffops/_directional_derivative.py
linpde_gp/linfuncops/diffops/_functions.py
linpde_gp/linfuncops/diffops/_heat.py
linpde_gp/linfuncops/diffops/_laplacian.py
linpde_gp/linfuncops/diffops/_lindiffop.py
linpde_gp/linfunctls/__init__.py
linpde_gp/linfunctls/_arithmetic.py
linpde_gp/linfunctls/_dirac.py
linpde_gp/linfunctls/_evaluation.py
linpde_gp/linfunctls/_integrals.py
linpde_gp/linfunctls/_linfunctl.py
linpde_gp-0.0.1.dist-info/LICENSE
linpde_gp-0.0.1.dist-info/METADATA
linpde_gp-0.0.1.dist-info/WHEEL
linpde_gp-0.0.1.dist-info/top_level.txt
linpde_gp-0.0.1.dist-info/RECORD
