Metadata-Version: 2.1
Name: linpde-gp
Version: 0.0.1
Summary: Linear PDE Solvers as Gaussian Process Inference
Author-email: Marvin Pförtner <marvin.pfoertner@uni-tuebingen.de>
License: MIT
Project-URL: github, https://github.com/marvinpfoertner/linpde-gp
Keywords: partial-differential-equations,gaussian-processes,probabilistic-numerics,galerkin-method,finite-element-method,collocation-method,spectral-methods
Platform: any
Classifier: License :: OSI Approved :: MIT License
Classifier: Operating System :: OS Independent
Classifier: Programming Language :: Python :: 3.10
Requires-Python: <3.11,>=3.10
License-File: LICENSE
Requires-Dist: numpy (>=1.21.3)
Requires-Dist: scipy (>=1.4)
Requires-Dist: probnum (<0.1.25,>=0.1.24)
Requires-Dist: jax[cpu] (>=0.2.18)
Requires-Dist: matplotlib (>=3.4.3)
Requires-Dist: pykeops (<3.0,>=2.1.1)
